aws_cfn_custom_resource_resolve_parser/__init__.py
aws_cfn_custom_resource_resolve_parser-0.3.2.dist-info/LICENSE
aws_cfn_custom_resource_resolve_parser-0.3.2.dist-info/METADATA
aws_cfn_custom_resource_resolve_parser-0.3.2.dist-info/WHEEL
aws_cfn_custom_resource_resolve_parser-0.3.2.dist-info/RECORD
